{
  "version": "1.0.0-zulu.270",
  "helmCharts": {
    "wire-server": {
      "repo": "https://s3-eu-west-1.amazonaws.com/public.wire.com/charts-develop",
      "version": "4.39.136",
      "meta": {
        "appVersion": "4.39.136",
        "commit": "6a77ffa5db7db885150d21dfb6ca55c1390355a4",
        "commitURL": "https://github.com/wireapp/wire-server/commit/6a77ffa5db7db885150d21dfb6ca55c1390355a4"
      }
    },
    "webapp": {
      "repo": "https://s3-eu-west-1.amazonaws.com/public.wire.com/charts-webapp",
      "version": "0.6.0-pre.79",
      "meta": {
        "appVersion": "dev-v0.31.20-fa7c10b",
        "commitURL": "https://github.com/wireapp/wire-webapp/commit/fa7c10b983527f2b4cea1f7a1782436cd8426322",
        "commit": "fa7c10b983527f2b4cea1f7a1782436cd8426322"
      }
    },
    "team-settings": {
      "repo": "https://s3-eu-west-1.amazonaws.com/public.wire.com/charts-webapp",
      "version": "0.1.0-pre.39",
      "meta": {
        "appVersion": "4.15.1-v0.31.19-380d894",
        "commitURL": "https://github.com/wireapp/wire-team-settings/commit/380d894a6a3c7b6f1851ee26f3b42c4ce17769e9",
        "commit": "380d894a6a3c7b6f1851ee26f3b42c4ce17769e9"
      }
    },
    "sftd": {
      "repo": "https://s3-eu-west-1.amazonaws.com/public.wire.com/charts-avs",
      "version": "0.20.0",
      "meta": {
        "appVersion": "4.0.19",
        "commit": "a9ba2f9"
      }
    },
    "aws-ingress": {
      "repo": "https://s3-eu-west-1.amazonaws.com/public.wire.com/charts-develop",
      "version": "4.39.136",
      "meta": {
        "appVersion": "4.39.136",
        "commit": "6a77ffa5db7db885150d21dfb6ca55c1390355a4",
        "commitURL": "https://github.com/wireapp/wire-server/commit/6a77ffa5db7db885150d21dfb6ca55c1390355a4"
      }
    },
    "backoffice": {
      "repo": "https://s3-eu-west-1.amazonaws.com/public.wire.com/charts-develop",
      "version": "4.39.136",
      "meta": {
        "appVersion": "4.39.136",
        "commit": "6a77ffa5db7db885150d21dfb6ca55c1390355a4",
        "commitURL": "https://github.com/wireapp/wire-server/commit/6a77ffa5db7db885150d21dfb6ca55c1390355a4"
      }
    },
    "calling-test": {
      "repo": "https://s3-eu-west-1.amazonaws.com/public.wire.com/charts-develop",
      "version": "4.39.136",
      "meta": {
        "appVersion": "4.39.136",
        "commit": "6a77ffa5db7db885150d21dfb6ca55c1390355a4",
        "commitURL": "https://github.com/wireapp/wire-server/commit/6a77ffa5db7db885150d21dfb6ca55c1390355a4"
      }
    },
    "cassandra-external": {
      "repo": "https://s3-eu-west-1.amazonaws.com/public.wire.com/charts-develop",
      "version": "4.39.136",
      "meta": {
        "appVersion": "4.39.136",
        "commit": "6a77ffa5db7db885150d21dfb6ca55c1390355a4",
        "commitURL": "https://github.com/wireapp/wire-server/commit/6a77ffa5db7db885150d21dfb6ca55c1390355a4"
      }
    },
    "coturn": {
      "repo": "https://s3-eu-west-1.amazonaws.com/public.wire.com/charts-develop",
      "version": "4.39.136",
      "meta": {
        "appVersion": "4.39.136",
        "commit": "6a77ffa5db7db885150d21dfb6ca55c1390355a4",
        "commitURL": "https://github.com/wireapp/wire-server/commit/6a77ffa5db7db885150d21dfb6ca55c1390355a4"
      }
    },
    "databases-ephemeral": {
      "repo": "https://s3-eu-west-1.amazonaws.com/public.wire.com/charts-develop",
      "version": "4.39.136",
      "meta": {
        "appVersion": "4.39.136",
        "commit": "6a77ffa5db7db885150d21dfb6ca55c1390355a4",
        "commitURL": "https://github.com/wireapp/wire-server/commit/6a77ffa5db7db885150d21dfb6ca55c1390355a4"
      }
    },
    "demo-smtp": {
      "repo": "https://s3-eu-west-1.amazonaws.com/public.wire.com/charts-develop",
      "version": "4.39.136",
      "meta": {
        "appVersion": "4.39.136",
        "commit": "6a77ffa5db7db885150d21dfb6ca55c1390355a4",
        "commitURL": "https://github.com/wireapp/wire-server/commit/6a77ffa5db7db885150d21dfb6ca55c1390355a4"
      }
    },
    "elasticsearch-curator": {
      "repo": "https://s3-eu-west-1.amazonaws.com/public.wire.com/charts-develop",
      "version": "4.39.136",
      "meta": {
        "appVersion": "4.39.136",
        "commit": "6a77ffa5db7db885150d21dfb6ca55c1390355a4",
        "commitURL": "https://github.com/wireapp/wire-server/commit/6a77ffa5db7db885150d21dfb6ca55c1390355a4"
      }
    },
    "elasticsearch-ephemeral": {
      "repo": "https://s3-eu-west-1.amazonaws.com/public.wire.com/charts-develop",
      "version": "4.39.136",
      "meta": {
        "appVersion": "4.39.136",
        "commit": "6a77ffa5db7db885150d21dfb6ca55c1390355a4",
        "commitURL": "https://github.com/wireapp/wire-server/commit/6a77ffa5db7db885150d21dfb6ca55c1390355a4"
      }
    },
    "elasticsearch-external": {
      "repo": "https://s3-eu-west-1.amazonaws.com/public.wire.com/charts-develop",
      "version": "4.39.136",
      "meta": {
        "appVersion": "4.39.136",
        "commit": "6a77ffa5db7db885150d21dfb6ca55c1390355a4",
        "commitURL": "https://github.com/wireapp/wire-server/commit/6a77ffa5db7db885150d21dfb6ca55c1390355a4"
      }
    },
    "fake-aws": {
      "repo": "https://s3-eu-west-1.amazonaws.com/public.wire.com/charts-develop",
      "version": "4.39.136",
      "meta": {
        "appVersion": "4.39.136",
        "commit": "6a77ffa5db7db885150d21dfb6ca55c1390355a4",
        "commitURL": "https://github.com/wireapp/wire-server/commit/6a77ffa5db7db885150d21dfb6ca55c1390355a4"
      }
    },
    "fake-aws-s3": {
      "repo": "https://s3-eu-west-1.amazonaws.com/public.wire.com/charts-develop",
      "version": "4.39.136",
      "meta": {
        "appVersion": "4.39.136",
        "commit": "6a77ffa5db7db885150d21dfb6ca55c1390355a4",
        "commitURL": "https://github.com/wireapp/wire-server/commit/6a77ffa5db7db885150d21dfb6ca55c1390355a4"
      }
    },
    "fake-aws-sqs": {
      "repo": "https://s3-eu-west-1.amazonaws.com/public.wire.com/charts-develop",
      "version": "4.39.136",
      "meta": {
        "appVersion": "4.39.136",
        "commit": "6a77ffa5db7db885150d21dfb6ca55c1390355a4",
        "commitURL": "https://github.com/wireapp/wire-server/commit/6a77ffa5db7db885150d21dfb6ca55c1390355a4"
      }
    },
    "fluent-bit": {
      "repo": "https://s3-eu-west-1.amazonaws.com/public.wire.com/charts-develop",
      "version": "4.39.136",
      "meta": {
        "appVersion": "4.39.136",
        "commit": "6a77ffa5db7db885150d21dfb6ca55c1390355a4",
        "commitURL": "https://github.com/wireapp/wire-server/commit/6a77ffa5db7db885150d21dfb6ca55c1390355a4"
      }
    },
    "inbucket": {
      "repo": "https://s3-eu-west-1.amazonaws.com/public.wire.com/charts-develop",
      "version": "4.39.136",
      "meta": {
        "appVersion": "4.39.136",
        "commit": "6a77ffa5db7db885150d21dfb6ca55c1390355a4",
        "commitURL": "https://github.com/wireapp/wire-server/commit/6a77ffa5db7db885150d21dfb6ca55c1390355a4"
      }
    },
    "ingress-nginx-controller": {
      "repo": "https://s3-eu-west-1.amazonaws.com/public.wire.com/charts-develop",
      "version": "4.39.136",
      "meta": {
        "appVersion": "4.39.136",
        "commit": "6a77ffa5db7db885150d21dfb6ca55c1390355a4",
        "commitURL": "https://github.com/wireapp/wire-server/commit/6a77ffa5db7db885150d21dfb6ca55c1390355a4"
      }
    },
    "k8ssandra-test-cluster": {
      "repo": "https://s3-eu-west-1.amazonaws.com/public.wire.com/charts-develop",
      "version": "4.39.136",
      "meta": {
        "appVersion": "4.39.136",
        "commit": "6a77ffa5db7db885150d21dfb6ca55c1390355a4",
        "commitURL": "https://github.com/wireapp/wire-server/commit/6a77ffa5db7db885150d21dfb6ca55c1390355a4"
      }
    },
    "kibana": {
      "repo": "https://s3-eu-west-1.amazonaws.com/public.wire.com/charts-develop",
      "version": "4.39.136",
      "meta": {
        "appVersion": "4.39.136",
        "commit": "6a77ffa5db7db885150d21dfb6ca55c1390355a4",
        "commitURL": "https://github.com/wireapp/wire-server/commit/6a77ffa5db7db885150d21dfb6ca55c1390355a4"
      }
    },
    "minio-external": {
      "repo": "https://s3-eu-west-1.amazonaws.com/public.wire.com/charts-develop",
      "version": "4.39.136",
      "meta": {
        "appVersion": "4.39.136",
        "commit": "6a77ffa5db7db885150d21dfb6ca55c1390355a4",
        "commitURL": "https://github.com/wireapp/wire-server/commit/6a77ffa5db7db885150d21dfb6ca55c1390355a4"
      }
    },
    "nginx-ingress-controller": {
      "repo": "https://s3-eu-west-1.amazonaws.com/public.wire.com/charts-develop",
      "version": "4.39.136",
      "meta": {
        "appVersion": "4.39.136",
        "commit": "6a77ffa5db7db885150d21dfb6ca55c1390355a4",
        "commitURL": "https://github.com/wireapp/wire-server/commit/6a77ffa5db7db885150d21dfb6ca55c1390355a4"
      }
    },
    "nginx-ingress-services": {
      "repo": "https://s3-eu-west-1.amazonaws.com/public.wire.com/charts-develop",
      "version": "4.39.136",
      "meta": {
        "appVersion": "4.39.136",
        "commit": "6a77ffa5db7db885150d21dfb6ca55c1390355a4",
        "commitURL": "https://github.com/wireapp/wire-server/commit/6a77ffa5db7db885150d21dfb6ca55c1390355a4"
      }
    },
    "postgresql": {
      "repo": "https://s3-eu-west-1.amazonaws.com/public.wire.com/charts-develop",
      "version": "4.39.136",
      "meta": {
        "appVersion": "4.39.136",
        "commit": "6a77ffa5db7db885150d21dfb6ca55c1390355a4",
        "commitURL": "https://github.com/wireapp/wire-server/commit/6a77ffa5db7db885150d21dfb6ca55c1390355a4"
      }
    },
    "rabbitmq": {
      "repo": "https://s3-eu-west-1.amazonaws.com/public.wire.com/charts-develop",
      "version": "4.39.136",
      "meta": {
        "appVersion": "4.39.136",
        "commit": "6a77ffa5db7db885150d21dfb6ca55c1390355a4",
        "commitURL": "https://github.com/wireapp/wire-server/commit/6a77ffa5db7db885150d21dfb6ca55c1390355a4"
      }
    },
    "rabbitmq-external": {
      "repo": "https://s3-eu-west-1.amazonaws.com/public.wire.com/charts-develop",
      "version": "4.39.136",
      "meta": {
        "appVersion": "4.39.136",
        "commit": "6a77ffa5db7db885150d21dfb6ca55c1390355a4",
        "commitURL": "https://github.com/wireapp/wire-server/commit/6a77ffa5db7db885150d21dfb6ca55c1390355a4"
      }
    },
    "reaper": {
      "repo": "https://s3-eu-west-1.amazonaws.com/public.wire.com/charts-develop",
      "version": "4.39.136",
      "meta": {
        "appVersion": "4.39.136",
        "commit": "6a77ffa5db7db885150d21dfb6ca55c1390355a4",
        "commitURL": "https://github.com/wireapp/wire-server/commit/6a77ffa5db7db885150d21dfb6ca55c1390355a4"
      }
    },
    "redis-cluster": {
      "repo": "https://s3-eu-west-1.amazonaws.com/public.wire.com/charts-develop",
      "version": "4.39.136",
      "meta": {
        "appVersion": "4.39.136",
        "commit": "6a77ffa5db7db885150d21dfb6ca55c1390355a4",
        "commitURL": "https://github.com/wireapp/wire-server/commit/6a77ffa5db7db885150d21dfb6ca55c1390355a4"
      }
    },
    "redis-ephemeral": {
      "repo": "https://s3-eu-west-1.amazonaws.com/public.wire.com/charts-develop",
      "version": "4.39.136",
      "meta": {
        "appVersion": "4.39.136",
        "commit": "6a77ffa5db7db885150d21dfb6ca55c1390355a4",
        "commitURL": "https://github.com/wireapp/wire-server/commit/6a77ffa5db7db885150d21dfb6ca55c1390355a4"
      }
    },
    "restund": {
      "repo": "https://s3-eu-west-1.amazonaws.com/public.wire.com/charts-develop",
      "version": "4.39.136",
      "meta": {
        "appVersion": "4.39.136",
        "commit": "6a77ffa5db7db885150d21dfb6ca55c1390355a4",
        "commitURL": "https://github.com/wireapp/wire-server/commit/6a77ffa5db7db885150d21dfb6ca55c1390355a4"
      }
    },
    "account-pages": {
      "repo": "https://s3-eu-west-1.amazonaws.com/public.wire.com/charts-webapp",
      "version": "0.1.0-pre.23",
      "meta": {
        "appVersion": "2.5.0-v0.31.15-66484d1",
        "commitURL": "https://github.com/wireapp/wire-account/commit/66484d1b3bb9e55c8eefdaea6b391ca526a4e3d4",
        "commit": "66484d1b3bb9e55c8eefdaea6b391ca526a4e3d4"
      }
    }
  }
}
