{
  "version": "1.0.0-zulu.353",
  "helmCharts": {
    "wire-server": {
      "repo": "https://s3-eu-west-1.amazonaws.com/public.wire.com/charts-develop",
      "version": "4.39.157",
      "meta": {
        "appVersion": "4.39.157",
        "commit": "14cb8712887a2a676727d9e086d0094fa833ed97",
        "commitURL": "https://github.com/wireapp/wire-server/commit/14cb8712887a2a676727d9e086d0094fa833ed97"
      }
    },
    "webapp": {
      "repo": "https://s3-eu-west-1.amazonaws.com/public.wire.com/charts-webapp",
      "version": "0.6.0-pre.165",
      "meta": {
        "appVersion": "dev-v0.31.21-69a1ba8",
        "commitURL": "https://github.com/wireapp/wire-webapp/commit/69a1ba89b8cfc36ebcc33f6b7a65a18c3dcedaf3",
        "commit": "69a1ba89b8cfc36ebcc33f6b7a65a18c3dcedaf3"
      }
    },
    "team-settings": {
      "repo": "https://s3-eu-west-1.amazonaws.com/public.wire.com/charts-webapp",
      "version": "0.1.0-pre.51",
      "meta": {
        "appVersion": "4.15.1-v0.31.19-67ca668",
        "commitURL": "https://github.com/wireapp/wire-team-settings/commit/67ca6688fc9ba1ea376f3557a8d3eda7b2df85b8",
        "commit": "67ca6688fc9ba1ea376f3557a8d3eda7b2df85b8"
      }
    },
    "sftd": {
      "repo": "https://s3-eu-west-1.amazonaws.com/public.wire.com/charts-avs",
      "version": "0.20.0",
      "meta": {
        "appVersion": "4.0.19",
        "commit": "a9ba2f9"
      }
    },
    "aws-ingress": {
      "repo": "https://s3-eu-west-1.amazonaws.com/public.wire.com/charts-develop",
      "version": "4.39.157",
      "meta": {
        "appVersion": "4.39.157",
        "commit": "14cb8712887a2a676727d9e086d0094fa833ed97",
        "commitURL": "https://github.com/wireapp/wire-server/commit/14cb8712887a2a676727d9e086d0094fa833ed97"
      }
    },
    "backoffice": {
      "repo": "https://s3-eu-west-1.amazonaws.com/public.wire.com/charts-develop",
      "version": "4.39.157",
      "meta": {
        "appVersion": "4.39.157",
        "commit": "14cb8712887a2a676727d9e086d0094fa833ed97",
        "commitURL": "https://github.com/wireapp/wire-server/commit/14cb8712887a2a676727d9e086d0094fa833ed97"
      }
    },
    "calling-test": {
      "repo": "https://s3-eu-west-1.amazonaws.com/public.wire.com/charts-develop",
      "version": "4.39.157",
      "meta": {
        "appVersion": "4.39.157",
        "commit": "14cb8712887a2a676727d9e086d0094fa833ed97",
        "commitURL": "https://github.com/wireapp/wire-server/commit/14cb8712887a2a676727d9e086d0094fa833ed97"
      }
    },
    "cassandra-external": {
      "repo": "https://s3-eu-west-1.amazonaws.com/public.wire.com/charts-develop",
      "version": "4.39.157",
      "meta": {
        "appVersion": "4.39.157",
        "commit": "14cb8712887a2a676727d9e086d0094fa833ed97",
        "commitURL": "https://github.com/wireapp/wire-server/commit/14cb8712887a2a676727d9e086d0094fa833ed97"
      }
    },
    "coturn": {
      "repo": "https://s3-eu-west-1.amazonaws.com/public.wire.com/charts-develop",
      "version": "4.39.157",
      "meta": {
        "appVersion": "4.39.157",
        "commit": "14cb8712887a2a676727d9e086d0094fa833ed97",
        "commitURL": "https://github.com/wireapp/wire-server/commit/14cb8712887a2a676727d9e086d0094fa833ed97"
      }
    },
    "databases-ephemeral": {
      "repo": "https://s3-eu-west-1.amazonaws.com/public.wire.com/charts-develop",
      "version": "4.39.157",
      "meta": {
        "appVersion": "4.39.157",
        "commit": "14cb8712887a2a676727d9e086d0094fa833ed97",
        "commitURL": "https://github.com/wireapp/wire-server/commit/14cb8712887a2a676727d9e086d0094fa833ed97"
      }
    },
    "demo-smtp": {
      "repo": "https://s3-eu-west-1.amazonaws.com/public.wire.com/charts-develop",
      "version": "4.39.157",
      "meta": {
        "appVersion": "4.39.157",
        "commit": "14cb8712887a2a676727d9e086d0094fa833ed97",
        "commitURL": "https://github.com/wireapp/wire-server/commit/14cb8712887a2a676727d9e086d0094fa833ed97"
      }
    },
    "elasticsearch-curator": {
      "repo": "https://s3-eu-west-1.amazonaws.com/public.wire.com/charts-develop",
      "version": "4.39.157",
      "meta": {
        "appVersion": "4.39.157",
        "commit": "14cb8712887a2a676727d9e086d0094fa833ed97",
        "commitURL": "https://github.com/wireapp/wire-server/commit/14cb8712887a2a676727d9e086d0094fa833ed97"
      }
    },
    "elasticsearch-ephemeral": {
      "repo": "https://s3-eu-west-1.amazonaws.com/public.wire.com/charts-develop",
      "version": "4.39.157",
      "meta": {
        "appVersion": "4.39.157",
        "commit": "14cb8712887a2a676727d9e086d0094fa833ed97",
        "commitURL": "https://github.com/wireapp/wire-server/commit/14cb8712887a2a676727d9e086d0094fa833ed97"
      }
    },
    "elasticsearch-external": {
      "repo": "https://s3-eu-west-1.amazonaws.com/public.wire.com/charts-develop",
      "version": "4.39.157",
      "meta": {
        "appVersion": "4.39.157",
        "commit": "14cb8712887a2a676727d9e086d0094fa833ed97",
        "commitURL": "https://github.com/wireapp/wire-server/commit/14cb8712887a2a676727d9e086d0094fa833ed97"
      }
    },
    "fake-aws": {
      "repo": "https://s3-eu-west-1.amazonaws.com/public.wire.com/charts-develop",
      "version": "4.39.157",
      "meta": {
        "appVersion": "4.39.157",
        "commit": "14cb8712887a2a676727d9e086d0094fa833ed97",
        "commitURL": "https://github.com/wireapp/wire-server/commit/14cb8712887a2a676727d9e086d0094fa833ed97"
      }
    },
    "fake-aws-s3": {
      "repo": "https://s3-eu-west-1.amazonaws.com/public.wire.com/charts-develop",
      "version": "4.39.157",
      "meta": {
        "appVersion": "4.39.157",
        "commit": "14cb8712887a2a676727d9e086d0094fa833ed97",
        "commitURL": "https://github.com/wireapp/wire-server/commit/14cb8712887a2a676727d9e086d0094fa833ed97"
      }
    },
    "fake-aws-sqs": {
      "repo": "https://s3-eu-west-1.amazonaws.com/public.wire.com/charts-develop",
      "version": "4.39.157",
      "meta": {
        "appVersion": "4.39.157",
        "commit": "14cb8712887a2a676727d9e086d0094fa833ed97",
        "commitURL": "https://github.com/wireapp/wire-server/commit/14cb8712887a2a676727d9e086d0094fa833ed97"
      }
    },
    "fluent-bit": {
      "repo": "https://s3-eu-west-1.amazonaws.com/public.wire.com/charts-develop",
      "version": "4.39.157",
      "meta": {
        "appVersion": "4.39.157",
        "commit": "14cb8712887a2a676727d9e086d0094fa833ed97",
        "commitURL": "https://github.com/wireapp/wire-server/commit/14cb8712887a2a676727d9e086d0094fa833ed97"
      }
    },
    "inbucket": {
      "repo": "https://s3-eu-west-1.amazonaws.com/public.wire.com/charts-develop",
      "version": "4.39.157",
      "meta": {
        "appVersion": "4.39.157",
        "commit": "14cb8712887a2a676727d9e086d0094fa833ed97",
        "commitURL": "https://github.com/wireapp/wire-server/commit/14cb8712887a2a676727d9e086d0094fa833ed97"
      }
    },
    "ingress-nginx-controller": {
      "repo": "https://s3-eu-west-1.amazonaws.com/public.wire.com/charts-develop",
      "version": "4.39.157",
      "meta": {
        "appVersion": "4.39.157",
        "commit": "14cb8712887a2a676727d9e086d0094fa833ed97",
        "commitURL": "https://github.com/wireapp/wire-server/commit/14cb8712887a2a676727d9e086d0094fa833ed97"
      }
    },
    "k8ssandra-test-cluster": {
      "repo": "https://s3-eu-west-1.amazonaws.com/public.wire.com/charts-develop",
      "version": "4.39.157",
      "meta": {
        "appVersion": "4.39.157",
        "commit": "14cb8712887a2a676727d9e086d0094fa833ed97",
        "commitURL": "https://github.com/wireapp/wire-server/commit/14cb8712887a2a676727d9e086d0094fa833ed97"
      }
    },
    "kibana": {
      "repo": "https://s3-eu-west-1.amazonaws.com/public.wire.com/charts-develop",
      "version": "4.39.157",
      "meta": {
        "appVersion": "4.39.157",
        "commit": "14cb8712887a2a676727d9e086d0094fa833ed97",
        "commitURL": "https://github.com/wireapp/wire-server/commit/14cb8712887a2a676727d9e086d0094fa833ed97"
      }
    },
    "minio-external": {
      "repo": "https://s3-eu-west-1.amazonaws.com/public.wire.com/charts-develop",
      "version": "4.39.157",
      "meta": {
        "appVersion": "4.39.157",
        "commit": "14cb8712887a2a676727d9e086d0094fa833ed97",
        "commitURL": "https://github.com/wireapp/wire-server/commit/14cb8712887a2a676727d9e086d0094fa833ed97"
      }
    },
    "nginx-ingress-controller": {
      "repo": "https://s3-eu-west-1.amazonaws.com/public.wire.com/charts-develop",
      "version": "4.39.157",
      "meta": {
        "appVersion": "4.39.157",
        "commit": "14cb8712887a2a676727d9e086d0094fa833ed97",
        "commitURL": "https://github.com/wireapp/wire-server/commit/14cb8712887a2a676727d9e086d0094fa833ed97"
      }
    },
    "nginx-ingress-services": {
      "repo": "https://s3-eu-west-1.amazonaws.com/public.wire.com/charts-develop",
      "version": "4.39.157",
      "meta": {
        "appVersion": "4.39.157",
        "commit": "14cb8712887a2a676727d9e086d0094fa833ed97",
        "commitURL": "https://github.com/wireapp/wire-server/commit/14cb8712887a2a676727d9e086d0094fa833ed97"
      }
    },
    "postgresql": {
      "repo": "https://s3-eu-west-1.amazonaws.com/public.wire.com/charts-develop",
      "version": "4.39.157",
      "meta": {
        "appVersion": "4.39.157",
        "commit": "14cb8712887a2a676727d9e086d0094fa833ed97",
        "commitURL": "https://github.com/wireapp/wire-server/commit/14cb8712887a2a676727d9e086d0094fa833ed97"
      }
    },
    "rabbitmq": {
      "repo": "https://s3-eu-west-1.amazonaws.com/public.wire.com/charts-develop",
      "version": "4.39.157",
      "meta": {
        "appVersion": "4.39.157",
        "commit": "14cb8712887a2a676727d9e086d0094fa833ed97",
        "commitURL": "https://github.com/wireapp/wire-server/commit/14cb8712887a2a676727d9e086d0094fa833ed97"
      }
    },
    "rabbitmq-external": {
      "repo": "https://s3-eu-west-1.amazonaws.com/public.wire.com/charts-develop",
      "version": "4.39.157",
      "meta": {
        "appVersion": "4.39.157",
        "commit": "14cb8712887a2a676727d9e086d0094fa833ed97",
        "commitURL": "https://github.com/wireapp/wire-server/commit/14cb8712887a2a676727d9e086d0094fa833ed97"
      }
    },
    "reaper": {
      "repo": "https://s3-eu-west-1.amazonaws.com/public.wire.com/charts-develop",
      "version": "4.39.157",
      "meta": {
        "appVersion": "4.39.157",
        "commit": "14cb8712887a2a676727d9e086d0094fa833ed97",
        "commitURL": "https://github.com/wireapp/wire-server/commit/14cb8712887a2a676727d9e086d0094fa833ed97"
      }
    },
    "redis-cluster": {
      "repo": "https://s3-eu-west-1.amazonaws.com/public.wire.com/charts-develop",
      "version": "4.39.157",
      "meta": {
        "appVersion": "4.39.157",
        "commit": "14cb8712887a2a676727d9e086d0094fa833ed97",
        "commitURL": "https://github.com/wireapp/wire-server/commit/14cb8712887a2a676727d9e086d0094fa833ed97"
      }
    },
    "redis-ephemeral": {
      "repo": "https://s3-eu-west-1.amazonaws.com/public.wire.com/charts-develop",
      "version": "4.39.157",
      "meta": {
        "appVersion": "4.39.157",
        "commit": "14cb8712887a2a676727d9e086d0094fa833ed97",
        "commitURL": "https://github.com/wireapp/wire-server/commit/14cb8712887a2a676727d9e086d0094fa833ed97"
      }
    },
    "restund": {
      "repo": "https://s3-eu-west-1.amazonaws.com/public.wire.com/charts-develop",
      "version": "4.39.157",
      "meta": {
        "appVersion": "4.39.157",
        "commit": "14cb8712887a2a676727d9e086d0094fa833ed97",
        "commitURL": "https://github.com/wireapp/wire-server/commit/14cb8712887a2a676727d9e086d0094fa833ed97"
      }
    },
    "account-pages": {
      "repo": "https://s3-eu-west-1.amazonaws.com/public.wire.com/charts-webapp",
      "version": "0.1.0-pre.30",
      "meta": {
        "appVersion": "2.5.0-v0.31.15-32601c7",
        "commitURL": "https://github.com/wireapp/wire-account/commit/32601c75a66a56fa0d5eb423b1abaeee2170b4dd",
        "commit": "32601c75a66a56fa0d5eb423b1abaeee2170b4dd"
      }
    }
  }
}
